gower_multiprocessing/__init__.py
gower_multiprocessing/gower_dist.py
gower_multiprocessing-0.2.2.dist-info/LICENSE
gower_multiprocessing-0.2.2.dist-info/METADATA
gower_multiprocessing-0.2.2.dist-info/WHEEL
gower_multiprocessing-0.2.2.dist-info/top_level.txt
gower_multiprocessing-0.2.2.dist-info/RECORD
