Metadata-Version: 2.1
Name: gower-multiprocessing
Version: 0.2.2
Summary: Python implementation of Gowers distance, pairwise between records in two data sets with multiprocessing support
Author: Michael Yan, Dominic D
Author-email: Szymon Bobek <szymon.bobek@gmail.com>
Project-URL: Homepage, https://github.com/sbobek/gower
Keywords: gower,distance,matrix
Classifier: Programming Language :: Python :: 3
Classifier: License :: OSI Approved :: MIT License
Classifier: Operating System :: OS Independent
Requires-Python: >=2.7
License-File: LICENSE
